cezzis_kafka/__init__.py
cezzis_kafka/__init__.pyi
cezzis_kafka/async_kafka_consumer.py
cezzis_kafka/async_kafka_consumer.pyi
cezzis_kafka/iasync_kafka_message_processor.py
cezzis_kafka/iasync_kafka_message_processor.pyi
cezzis_kafka/ikafka_message_processor.py
cezzis_kafka/ikafka_message_processor.pyi
cezzis_kafka/kafka_consumer.py
cezzis_kafka/kafka_consumer.pyi
cezzis_kafka/kafka_consumer_settings.py
cezzis_kafka/kafka_consumer_settings.pyi
cezzis_kafka/kafka_producer.py
cezzis_kafka/kafka_producer.pyi
cezzis_kafka/kafka_producer_settings.py
cezzis_kafka/kafka_producer_settings.pyi
cezzis_kafka-0.0.25.dist-info/METADATA
cezzis_kafka-0.0.25.dist-info/WHEEL
cezzis_kafka-0.0.25.dist-info/RECORD
