Metadata-Version: 2.4
Name: cezzis_kafka
Version: 0.0.25
Summary: cezzis-kafka is a lightweight Python library for working with Kafka topics and event streams. It simplifies producing, consuming, and managing messages, enabling seamless integration with distributed systems and real-time data pipelines. Designed for flexibility and ease of use, cezzis-kafka supports both synchronous and asynchronous workflows.
License: MIT
Author: mtnvencenzo
Author-email: rvecchi@gmail.com
Requires-Python: >=3.12,<3.15
Classifier: License :: OSI Approved :: MIT License
Classifier: Programming Language :: Python :: 3
Classifier: Programming Language :: Python :: 3.12
Classifier: Programming Language :: Python :: 3.13
Classifier: Programming Language :: Python :: 3.14
Requires-Dist: confluent-kafka (>=2.12.1,<3.0.0)
Requires-Dist: types-confluent-kafka (>=1.4.0,<2.0.0)
